{
  "annotations": {
    "list": [
      {
        "builtIn": 1,
        "datasource": {
          "type": "grafana",
          "uid": "-- Grafana --"
        },
        "enable": true,
        "hide": true,
        "iconColor": "rgba(0, 211, 255, 1)",
        "name": "Annotations & Alerts",
        "type": "dashboard"
      }
    ]
  },
  "editable": true,
  "fiscalYearStartMonth": 0,
  "graphTooltip": 0,
  "links": [],
  "panels": [
    {
      "collapsed": true,
      "gridPos": {
        "h": 1,
        "w": 24,
        "x": 0,
        "y": 0
      },
      "id": 31,
      "panels": [
        {
          "datasource": {
            "type": "datasource",
            "uid": "-- Mixed --"
          },
          "gridPos": {
            "h": 30,
            "w": 24,
            "x": 0,
            "y": 1
          },
          "id": 30,
          "options": {
            "code": {
              "language": "plaintext",
              "showLineNumbers": false,
              "showMiniMap": false
            },
            "content": "## Summary ##\nThis dashboard features a comparison between the real amount of element and volumes in the database in regards with the budgeted values given in the technical budget thanks to red thresholds displayed on graphs.\n\nThe dashboard is split in 2 rows:\n- The first row gives a global overview per service type : ```Production, Archiving and Dissemination``` per satellite. In green, the volume/count in our database and in red the budgeted value. The satelite and mission can be chosen\n\n- The second row gives a more detailled view where user can also choose a specific technocal budget level and timeliness for a giner granularity\n \n\n## Timeliness lookup table ##\n\nTo match the timeliness written in the technical budget with the one from our database, the following true table has been used\n\n    Technical budget MISSION // Technical budget Timeliness // Database timelinesses\n\n    S1    ///    NTC      ///   [\"NTC\"]\n    S1    ///    NRT:     ///   [\"NRT\",\"NRT-PT\"]\n    S1    ///    A        ///   [\"NRT-PT\",\"NTC\",\"NRT\"]\n    S1    ///    AUX      ///   [\"_\"]\n    S1    ///    _        ///   [\"_\"]\n\n\n    S2    ///    NTC      ///   [\"NOMINAL,NOT_RECORDING\"]\n    S2    ///    AUX      ///   [\"AUX\"]\n    S2    ///    _        ///   [\"_\"]\n\n\n    S3    ///    NTC      ///   [\"NT\"]\n    S3    ///    NRT      ///   [\"NR,AL\"]\n    S3    ///    STC      ///   [\"ST\"]\n    S3    ///    AUX      ///   [\"SN,NS,NN,_\"]\n\n\n    S5    ///    NTC      ///   [\"OPER,OFFL\"]\n    S5    ///    AUX      ///   [\"_\"]\n    S5    ///    NRT      ///   [\"NRTI\"]\n\n\n## Facts related to technical budget v1.8 ##\n\n- element in technical budget with level L1X are rattached to L1.  EG: L1B -> L1  etc..\n\n- the typo in technical budget  type ```OFFL_L2__HCCO_``` instead of ```OFFL_L2__HCHO_``` has been taken into account in our calculation\n\n- type ```OBS_SS__` ``` is not an AUX and has not level so it has been disregarded from our calculation\n\n- All auxiliary have their level defined to ```AUX``` even if not written in the databudget\n\n- Some types in the technical budget have a suffix which does not exist for elements in our database ```(AUX_ECE)   (EUP)   (SH/SV/DH/DV)  (SH/SV) ``` so they have been removed to match with our data\n\n- Somes element in the databudget have their field ```#Num/day``` and/or ```Volume per day [GB]``` not defined. It will lead to an incomplete threshold definition\n\n- Some element for mission S1 have their level set to A without a timeliness defined. We kept them in a separate A level and we associated it to timeliness [\"NRT-PT\",\"NTC\",\"NRT\"] as a guess\n\n## Note ## \n- It is possible to select the version of the technical budget to use by modifying the version variable\n- The granularity of the data is a day\n\n\n Tables & timelines can only display up to 10 000 entries. Please make use of filters to narrow down the retrieved data and get a more realistic view.\",\n",
            "mode": "markdown"
          },
          "pluginVersion": "10.4.1",
          "title": "Description",
          "type": "text"
        }
      ],
      "title": "Dashboard Description",
      "type": "row"
    },
    {
      "collapsed": false,
      "gridPos": {
        "h": 1,
        "w": 24,
        "x": 0,
        "y": 1
      },
      "id": 7,
      "panels": [],
      "title": "Global Threshold",
      "type": "row"
    },
    {
      "datasource": {
        "type": "elasticsearch",
        "uid": "P9C1AEFD5EC435EE7"
      },
      "description": "",
      "fieldConfig": {
        "defaults": {
          "color": {
            "mode": "thresholds"
          },
          "mappings": [],
          "thresholds": {
            "mode": "absolute",
            "steps": [
              {
                "color": "green",
                "value": null
              }
            ]
          },
          "unit": "decgbytes"
        },
        "overrides": []
      },
      "gridPos": {
        "h": 3,
        "w": 8,
        "x": 0,
        "y": 2
      },
      "id": 24,
      "options": {
        "colorMode": "value",
        "graphMode": "area",
        "justifyMode": "auto",
        "orientation": "auto",
        "reduceOptions": {
          "calcs": [
            "lastNotNull"
          ],
          "fields": "",
          "values": false
        },
        "showPercentChange": false,
        "textMode": "auto",
        "wideLayout": true
      },
      "pluginVersion": "10.4.1",
      "targets": [
        {
          "datasource": {
            "name": "Expression",
            "type": "__expr__",
            "uid": "__expr__"
          },
          "expression": "$global_threshold_volume_produced",
          "hide": false,
          "refId": "B",
          "type": "math"
        }
      ],
      "title": "Global Threshold PRIP $satellite_unit",
      "type": "stat"
    },
    {
      "datasource": {
        "type": "elasticsearch",
        "uid": "P9C1AEFD5EC435EE7"
      },
      "description": "",
      "fieldConfig": {
        "defaults": {
          "color": {
            "mode": "thresholds"
          },
          "mappings": [],
          "thresholds": {
            "mode": "absolute",
            "steps": [
              {
                "color": "green",
                "value": null
              }
            ]
          },
          "unit": "decgbytes"
        },
        "overrides": []
      },
      "gridPos": {
        "h": 3,
        "w": 8,
        "x": 8,
        "y": 2
      },
      "id": 25,
      "options": {
        "colorMode": "value",
        "graphMode": "area",
        "justifyMode": "auto",
        "orientation": "auto",
        "reduceOptions": {
          "calcs": [
            "lastNotNull"
          ],
          "fields": "",
          "values": false
        },
        "showPercentChange": false,
        "textMode": "auto",
        "wideLayout": true
      },
      "pluginVersion": "10.4.1",
      "targets": [
        {
          "datasource": {
            "name": "Expression",
            "type": "__expr__",
            "uid": "__expr__"
          },
          "expression": "$global_threshold_volume_archived",
          "hide": false,
          "refId": "B",
          "type": "math"
        }
      ],
      "title": "Global Threshold LTA $satellite_unit",
      "type": "stat"
    },
    {
      "datasource": {
        "type": "elasticsearch",
        "uid": "P9C1AEFD5EC435EE7"
      },
      "description": "",
      "fieldConfig": {
        "defaults": {
          "color": {
            "mode": "thresholds"
          },
          "mappings": [],
          "thresholds": {
            "mode": "absolute",
            "steps": [
              {
                "color": "green",
                "value": null
              }
            ]
          },
          "unit": "decgbytes"
        },
        "overrides": []
      },
      "gridPos": {
        "h": 3,
        "w": 8,
        "x": 16,
        "y": 2
      },
      "id": 26,
      "options": {
        "colorMode": "value",
        "graphMode": "area",
        "justifyMode": "auto",
        "orientation": "auto",
        "reduceOptions": {
          "calcs": [
            "lastNotNull"
          ],
          "fields": "",
          "values": false
        },
        "showPercentChange": false,
        "textMode": "auto",
        "wideLayout": true
      },
      "pluginVersion": "10.4.1",
      "targets": [
        {
          "datasource": {
            "name": "Expression",
            "type": "__expr__",
            "uid": "__expr__"
          },
          "expression": "$global_threshold_volume_disseminated",
          "hide": false,
          "refId": "B",
          "type": "math"
        }
      ],
      "title": "Global Dissemination LTA $satellite_unit",
      "type": "stat"
    },
    {
      "datasource": {
        "type": "elasticsearch",
        "uid": "P9C1AEFD5EC435EE7"
      },
      "fieldConfig": {
        "defaults": {
          "color": {
            "mode": "palette-classic"
          },
          "custom": {
            "axisBorderShow": false,
            "axisCenteredZero": false,
            "axisColorMode": "text",
            "axisLabel": "",
            "axisPlacement": "auto",
            "barAlignment": 0,
            "drawStyle": "line",
            "fillOpacity": 0,
            "gradientMode": "none",
            "hideFrom": {
              "legend": false,
              "tooltip": false,
              "viz": false
            },
            "insertNulls": false,
            "lineInterpolation": "linear",
            "lineWidth": 1,
            "pointSize": 5,
            "scaleDistribution": {
              "type": "linear"
            },
            "showPoints": "auto",
            "spanNulls": false,
            "stacking": {
              "group": "A",
              "mode": "none"
            },
            "thresholdsStyle": {
              "mode": "line"
            }
          },
          "mappings": [],
          "thresholds": {
            "mode": "absolute",
            "steps": [
              {
                "color": "dark-orange",
                "value": null
              }
            ]
          },
          "unit": "decgbytes"
        },
        "overrides": [
          {
            "__systemRef": "hideSeriesFrom",
            "matcher": {
              "id": "byNames",
              "options": {
                "mode": "exclude",
                "names": [
                  "Volume In GB in database"
                ],
                "prefix": "All except:",
                "readOnly": true
              }
            },
            "properties": [
              {
                "id": "custom.hideFrom",
                "value": {
                  "legend": false,
                  "tooltip": false,
                  "viz": true
                }
              }
            ]
          }
        ]
      },
      "gridPos": {
        "h": 7,
        "w": 8,
        "x": 0,
        "y": 5
      },
      "id": 4,
      "maxPerRow": 6,
      "options": {
        "legend": {
          "calcs": [],
          "displayMode": "list",
          "placement": "bottom",
          "showLegend": true
        },
        "tooltip": {
          "mode": "single",
          "sort": "none"
        }
      },
      "pluginVersion": "10.3.1",
      "repeat": "service_type",
      "repeatDirection": "h",
      "targets": [
        {
          "alias": "Volume In GB in database",
          "bucketAggs": [
            {
              "field": "sensing_start_date",
              "id": "2",
              "settings": {
                "interval": "1d"
              },
              "type": "date_histogram"
            }
          ],
          "datasource": {
            "type": "elasticsearch",
            "uid": "P9C1AEFD5EC435EE7"
          },
          "hide": false,
          "metrics": [
            {
              "field": "content_length",
              "id": "1",
              "settings": {
                "script": "_value / 1000000000"
              },
              "type": "sum"
            }
          ],
          "query": "mission:$mission AND satellite_unit:$satellite_unit AND service_type:PRIP AND product_type:$global_type_produced",
          "refId": "A",
          "timeField": "sensing_start_date"
        },
        {
          "datasource": {
            "name": "Expression",
            "type": "__expr__",
            "uid": "__expr__"
          },
          "expression": "$global_threshold_volume_produced",
          "hide": false,
          "refId": "B",
          "type": "math"
        }
      ],
      "title": "PRIP Data Volume",
      "transformations": [
        {
          "id": "configFromData",
          "options": {
            "configRefId": "B",
            "mappings": [
              {
                "fieldName": "B",
                "handlerKey": "threshold1"
              }
            ]
          }
        }
      ],
      "type": "timeseries"
    },
    {
      "datasource": {
        "type": "elasticsearch",
        "uid": "P9C1AEFD5EC435EE7"
      },
      "fieldConfig": {
        "defaults": {
          "color": {
            "mode": "palette-classic"
          },
          "custom": {
            "axisBorderShow": false,
            "axisCenteredZero": false,
            "axisColorMode": "text",
            "axisLabel": "",
            "axisPlacement": "auto",
            "barAlignment": 0,
            "drawStyle": "line",
            "fillOpacity": 0,
            "gradientMode": "none",
            "hideFrom": {
              "legend": false,
              "tooltip": false,
              "viz": false
            },
            "insertNulls": false,
            "lineInterpolation": "linear",
            "lineWidth": 1,
            "pointSize": 5,
            "scaleDistribution": {
              "type": "linear"
            },
            "showPoints": "auto",
            "spanNulls": false,
            "stacking": {
              "group": "A",
              "mode": "none"
            },
            "thresholdsStyle": {
              "mode": "line"
            }
          },
          "mappings": [],
          "thresholds": {
            "mode": "absolute",
            "steps": [
              {
                "color": "green",
                "value": null
              }
            ]
          },
          "unit": "decgbytes"
        },
        "overrides": []
      },
      "gridPos": {
        "h": 7,
        "w": 8,
        "x": 8,
        "y": 5
      },
      "id": 5,
      "maxPerRow": 6,
      "options": {
        "legend": {
          "calcs": [],
          "displayMode": "list",
          "placement": "bottom",
          "showLegend": true
        },
        "tooltip": {
          "mode": "single",
          "sort": "none"
        }
      },
      "pluginVersion": "10.3.1",
      "repeatDirection": "h",
      "targets": [
        {
          "alias": "Volume In GB in database",
          "bucketAggs": [
            {
              "field": "sensing_start_date",
              "id": "2",
              "settings": {
                "interval": "1d"
              },
              "type": "date_histogram"
            }
          ],
          "datasource": {
            "type": "elasticsearch",
            "uid": "P9C1AEFD5EC435EE7"
          },
          "hide": false,
          "metrics": [
            {
              "field": "content_length",
              "id": "1",
              "settings": {
                "script": "_value / 1000000000"
              },
              "type": "sum"
            }
          ],
          "query": "mission:$mission AND satellite_unit:$satellite_unit AND service_type:LTA AND service_id:$lta_provider AND product_type:$global_type_archived",
          "refId": "A",
          "timeField": "sensing_start_date"
        },
        {
          "datasource": {
            "name": "Expression",
            "type": "__expr__",
            "uid": "__expr__"
          },
          "expression": "$global_threshold_volume_archived",
          "hide": false,
          "refId": "B",
          "type": "math"
        }
      ],
      "title": "LTA Data Volume",
      "transformations": [
        {
          "id": "configFromData",
          "options": {
            "configRefId": "B",
            "mappings": [
              {
                "fieldName": "B",
                "handlerKey": "threshold1"
              }
            ]
          }
        }
      ],
      "type": "timeseries"
    },
    {
      "datasource": {
        "type": "elasticsearch",
        "uid": "P9C1AEFD5EC435EE7"
      },
      "fieldConfig": {
        "defaults": {
          "color": {
            "mode": "palette-classic"
          },
          "custom": {
            "axisBorderShow": false,
            "axisCenteredZero": false,
            "axisColorMode": "text",
            "axisLabel": "",
            "axisPlacement": "auto",
            "barAlignment": 0,
            "drawStyle": "line",
            "fillOpacity": 0,
            "gradientMode": "none",
            "hideFrom": {
              "legend": false,
              "tooltip": false,
              "viz": false
            },
            "insertNulls": false,
            "lineInterpolation": "linear",
            "lineWidth": 1,
            "pointSize": 5,
            "scaleDistribution": {
              "type": "linear"
            },
            "showPoints": "auto",
            "spanNulls": false,
            "stacking": {
              "group": "A",
              "mode": "none"
            },
            "thresholdsStyle": {
              "mode": "line"
            }
          },
          "mappings": [],
          "thresholds": {
            "mode": "absolute",
            "steps": [
              {
                "color": "green",
                "value": null
              }
            ]
          },
          "unit": "decgbytes"
        },
        "overrides": []
      },
      "gridPos": {
        "h": 7,
        "w": 8,
        "x": 16,
        "y": 5
      },
      "id": 6,
      "maxPerRow": 6,
      "options": {
        "legend": {
          "calcs": [],
          "displayMode": "list",
          "placement": "bottom",
          "showLegend": true
        },
        "tooltip": {
          "mode": "single",
          "sort": "none"
        }
      },
      "pluginVersion": "10.3.1",
      "repeatDirection": "h",
      "targets": [
        {
          "alias": "Volume In GB in database",
          "bucketAggs": [
            {
              "field": "sensing_start_date",
              "id": "2",
              "settings": {
                "interval": "1d"
              },
              "type": "date_histogram"
            }
          ],
          "datasource": {
            "type": "elasticsearch",
            "uid": "P9C1AEFD5EC435EE7"
          },
          "hide": false,
          "metrics": [
            {
              "field": "content_length",
              "id": "1",
              "settings": {
                "script": "_value / 1000000000"
              },
              "type": "sum"
            }
          ],
          "query": "mission:$mission AND satellite_unit:$satellite_unit AND service_type:DD AND product_type:$global_type_disseminated",
          "refId": "A",
          "timeField": "sensing_start_date"
        },
        {
          "datasource": {
            "name": "Expression",
            "type": "__expr__",
            "uid": "__expr__"
          },
          "expression": "$global_threshold_volume_disseminated",
          "hide": false,
          "refId": "B",
          "type": "math"
        }
      ],
      "title": "Dissemination Data Volume",
      "transformations": [
        {
          "id": "configFromData",
          "options": {
            "configRefId": "B",
            "mappings": [
              {
                "fieldName": "B",
                "handlerKey": "threshold1"
              }
            ]
          }
        }
      ],
      "type": "timeseries"
    },
    {
      "datasource": {
        "type": "elasticsearch",
        "uid": "P9C1AEFD5EC435EE7"
      },
      "description": "",
      "fieldConfig": {
        "defaults": {
          "color": {
            "mode": "thresholds"
          },
          "mappings": [],
          "thresholds": {
            "mode": "absolute",
            "steps": [
              {
                "color": "green",
                "value": null
              }
            ]
          },
          "unit": "none"
        },
        "overrides": []
      },
      "gridPos": {
        "h": 3,
        "w": 8,
        "x": 0,
        "y": 12
      },
      "id": 27,
      "options": {
        "colorMode": "value",
        "graphMode": "area",
        "justifyMode": "auto",
        "orientation": "auto",
        "reduceOptions": {
          "calcs": [
            "lastNotNull"
          ],
          "fields": "",
          "values": false
        },
        "showPercentChange": false,
        "textMode": "auto",
        "wideLayout": true
      },
      "pluginVersion": "10.4.1",
      "targets": [
        {
          "datasource": {
            "name": "Expression",
            "type": "__expr__",
            "uid": "__expr__"
          },
          "expression": "$global_threshold_count_produced",
          "hide": false,
          "refId": "B",
          "type": "math"
        }
      ],
      "title": "Global Threshold PRIP Count $satellite_unit",
      "type": "stat"
    },
    {
      "datasource": {
        "type": "elasticsearch",
        "uid": "P9C1AEFD5EC435EE7"
      },
      "description": "",
      "fieldConfig": {
        "defaults": {
          "color": {
            "mode": "thresholds"
          },
          "mappings": [],
          "thresholds": {
            "mode": "absolute",
            "steps": [
              {
                "color": "green",
                "value": null
              }
            ]
          },
          "unit": "none"
        },
        "overrides": []
      },
      "gridPos": {
        "h": 3,
        "w": 8,
        "x": 8,
        "y": 12
      },
      "id": 28,
      "options": {
        "colorMode": "value",
        "graphMode": "area",
        "justifyMode": "auto",
        "orientation": "auto",
        "reduceOptions": {
          "calcs": [
            "lastNotNull"
          ],
          "fields": "",
          "values": false
        },
        "showPercentChange": false,
        "textMode": "auto",
        "wideLayout": true
      },
      "pluginVersion": "10.4.1",
      "targets": [
        {
          "datasource": {
            "name": "Expression",
            "type": "__expr__",
            "uid": "__expr__"
          },
          "expression": "$global_threshold_count_archived",
          "hide": false,
          "refId": "B",
          "type": "math"
        }
      ],
      "title": "Global Threshold LTA Count $satellite_unit",
      "type": "stat"
    },
    {
      "datasource": {
        "type": "elasticsearch",
        "uid": "P9C1AEFD5EC435EE7"
      },
      "description": "",
      "fieldConfig": {
        "defaults": {
          "color": {
            "mode": "thresholds"
          },
          "mappings": [],
          "thresholds": {
            "mode": "absolute",
            "steps": [
              {
                "color": "green",
                "value": null
              }
            ]
          },
          "unit": "none"
        },
        "overrides": []
      },
      "gridPos": {
        "h": 3,
        "w": 8,
        "x": 16,
        "y": 12
      },
      "id": 29,
      "options": {
        "colorMode": "value",
        "graphMode": "area",
        "justifyMode": "auto",
        "orientation": "auto",
        "reduceOptions": {
          "calcs": [
            "lastNotNull"
          ],
          "fields": "",
          "values": false
        },
        "showPercentChange": false,
        "textMode": "auto",
        "wideLayout": true
      },
      "pluginVersion": "10.4.1",
      "targets": [
        {
          "datasource": {
            "name": "Expression",
            "type": "__expr__",
            "uid": "__expr__"
          },
          "expression": "$global_threshold_count_disseminated",
          "hide": false,
          "refId": "B",
          "type": "math"
        }
      ],
      "title": "Global Threshold Dissemination Count $satellite_unit",
      "type": "stat"
    },
    {
      "datasource": {
        "type": "elasticsearch",
        "uid": "P9C1AEFD5EC435EE7"
      },
      "fieldConfig": {
        "defaults": {
          "color": {
            "mode": "palette-classic"
          },
          "custom": {
            "axisBorderShow": false,
            "axisCenteredZero": false,
            "axisColorMode": "text",
            "axisLabel": "",
            "axisPlacement": "auto",
            "barAlignment": 0,
            "drawStyle": "line",
            "fillOpacity": 0,
            "gradientMode": "none",
            "hideFrom": {
              "legend": false,
              "tooltip": false,
              "viz": false
            },
            "insertNulls": false,
            "lineInterpolation": "linear",
            "lineWidth": 1,
            "pointSize": 5,
            "scaleDistribution": {
              "type": "linear"
            },
            "showPoints": "auto",
            "spanNulls": false,
            "stacking": {
              "group": "A",
              "mode": "none"
            },
            "thresholdsStyle": {
              "mode": "line"
            }
          },
          "mappings": [],
          "thresholds": {
            "mode": "absolute",
            "steps": [
              {
                "color": "green",
                "value": null
              }
            ]
          },
          "unit": "none"
        },
        "overrides": []
      },
      "gridPos": {
        "h": 7,
        "w": 8,
        "x": 0,
        "y": 15
      },
      "id": 8,
      "maxPerRow": 6,
      "options": {
        "legend": {
          "calcs": [],
          "displayMode": "list",
          "placement": "bottom",
          "showLegend": true
        },
        "tooltip": {
          "mode": "single",
          "sort": "none"
        }
      },
      "pluginVersion": "10.3.1",
      "repeatDirection": "h",
      "targets": [
        {
          "alias": "Number of document in database",
          "bucketAggs": [
            {
              "field": "sensing_start_date",
              "id": "2",
              "settings": {
                "interval": "1d"
              },
              "type": "date_histogram"
            }
          ],
          "datasource": {
            "type": "elasticsearch",
            "uid": "P9C1AEFD5EC435EE7"
          },
          "hide": false,
          "metrics": [
            {
              "id": "1",
              "type": "count"
            }
          ],
          "query": "mission:$mission AND satellite_unit:$satellite_unit AND service_type:PRIP  AND product_type:$global_type_produced",
          "refId": "A",
          "timeField": "sensing_start_date"
        },
        {
          "datasource": {
            "name": "Expression",
            "type": "__expr__",
            "uid": "__expr__"
          },
          "expression": "$global_threshold_count_produced",
          "hide": false,
          "refId": "B",
          "type": "math"
        }
      ],
      "title": "PRIP Data Count",
      "transformations": [
        {
          "id": "configFromData",
          "options": {
            "configRefId": "B",
            "mappings": [
              {
                "fieldName": "B",
                "handlerKey": "threshold1"
              }
            ]
          }
        }
      ],
      "type": "timeseries"
    },
    {
      "datasource": {
        "type": "elasticsearch",
        "uid": "P9C1AEFD5EC435EE7"
      },
      "fieldConfig": {
        "defaults": {
          "color": {
            "mode": "palette-classic"
          },
          "custom": {
            "axisBorderShow": false,
            "axisCenteredZero": false,
            "axisColorMode": "text",
            "axisLabel": "",
            "axisPlacement": "auto",
            "barAlignment": 0,
            "drawStyle": "line",
            "fillOpacity": 0,
            "gradientMode": "none",
            "hideFrom": {
              "legend": false,
              "tooltip": false,
              "viz": false
            },
            "insertNulls": false,
            "lineInterpolation": "linear",
            "lineWidth": 1,
            "pointSize": 5,
            "scaleDistribution": {
              "type": "linear"
            },
            "showPoints": "auto",
            "spanNulls": false,
            "stacking": {
              "group": "A",
              "mode": "none"
            },
            "thresholdsStyle": {
              "mode": "line"
            }
          },
          "mappings": [],
          "thresholds": {
            "mode": "absolute",
            "steps": [
              {
                "color": "green",
                "value": null
              }
            ]
          },
          "unit": "none"
        },
        "overrides": []
      },
      "gridPos": {
        "h": 7,
        "w": 8,
        "x": 8,
        "y": 15
      },
      "id": 9,
      "maxPerRow": 6,
      "options": {
        "legend": {
          "calcs": [],
          "displayMode": "list",
          "placement": "bottom",
          "showLegend": true
        },
        "tooltip": {
          "mode": "single",
          "sort": "none"
        }
      },
      "pluginVersion": "10.3.1",
      "repeatDirection": "h",
      "targets": [
        {
          "alias": "Number of document in database",
          "bucketAggs": [
            {
              "field": "sensing_start_date",
              "id": "2",
              "settings": {
                "interval": "1d"
              },
              "type": "date_histogram"
            }
          ],
          "datasource": {
            "type": "elasticsearch",
            "uid": "P9C1AEFD5EC435EE7"
          },
          "hide": false,
          "metrics": [
            {
              "id": "1",
              "type": "count"
            }
          ],
          "query": "mission:$mission AND satellite_unit:$satellite_unit AND service_type:LTA AND service_id:$lta_provider  AND product_type:$global_type_archived",
          "refId": "A",
          "timeField": "sensing_start_date"
        },
        {
          "datasource": {
            "name": "Expression",
            "type": "__expr__",
            "uid": "__expr__"
          },
          "expression": "$global_threshold_count_archived",
          "hide": false,
          "refId": "B",
          "type": "math"
        }
      ],
      "title": "LTA Data Count",
      "transformations": [
        {
          "id": "configFromData",
          "options": {
            "configRefId": "B",
            "mappings": [
              {
                "fieldName": "B",
                "handlerKey": "threshold1"
              }
            ]
          }
        }
      ],
      "type": "timeseries"
    },
    {
      "datasource": {
        "type": "elasticsearch",
        "uid": "P9C1AEFD5EC435EE7"
      },
      "fieldConfig": {
        "defaults": {
          "color": {
            "mode": "palette-classic"
          },
          "custom": {
            "axisBorderShow": false,
            "axisCenteredZero": false,
            "axisColorMode": "text",
            "axisLabel": "",
            "axisPlacement": "auto",
            "barAlignment": 0,
            "drawStyle": "line",
            "fillOpacity": 0,
            "gradientMode": "none",
            "hideFrom": {
              "legend": false,
              "tooltip": false,
              "viz": false
            },
            "insertNulls": false,
            "lineInterpolation": "linear",
            "lineWidth": 1,
            "pointSize": 5,
            "scaleDistribution": {
              "type": "linear"
            },
            "showPoints": "auto",
            "spanNulls": false,
            "stacking": {
              "group": "A",
              "mode": "none"
            },
            "thresholdsStyle": {
              "mode": "line"
            }
          },
          "mappings": [],
          "thresholds": {
            "mode": "absolute",
            "steps": [
              {
                "color": "green",
                "value": null
              }
            ]
          },
          "unit": "none"
        },
        "overrides": []
      },
      "gridPos": {
        "h": 7,
        "w": 8,
        "x": 16,
        "y": 15
      },
      "id": 10,
      "maxPerRow": 6,
      "options": {
        "legend": {
          "calcs": [],
          "displayMode": "list",
          "placement": "bottom",
          "showLegend": true
        },
        "tooltip": {
          "mode": "single",
          "sort": "none"
        }
      },
      "pluginVersion": "10.3.1",
      "repeatDirection": "h",
      "targets": [
        {
          "alias": "Number of document in database",
          "bucketAggs": [
            {
              "field": "sensing_start_date",
              "id": "2",
              "settings": {
                "interval": "1d"
              },
              "type": "date_histogram"
            }
          ],
          "datasource": {
            "type": "elasticsearch",
            "uid": "P9C1AEFD5EC435EE7"
          },
          "hide": false,
          "metrics": [
            {
              "id": "1",
              "type": "count"
            }
          ],
          "query": "mission:$mission AND satellite_unit:$satellite_unit AND service_type:DD  AND product_type:$global_type_disseminated",
          "refId": "A",
          "timeField": "sensing_start_date"
        },
        {
          "datasource": {
            "name": "Expression",
            "type": "__expr__",
            "uid": "__expr__"
          },
          "expression": "$global_threshold_count_disseminated",
          "hide": false,
          "refId": "B",
          "type": "math"
        }
      ],
      "title": "Dissemination Data Count",
      "transformations": [
        {
          "id": "configFromData",
          "options": {
            "configRefId": "B",
            "mappings": [
              {
                "fieldName": "B",
                "handlerKey": "threshold1"
              }
            ]
          }
        }
      ],
      "type": "timeseries"
    },
    {
      "collapsed": false,
      "gridPos": {
        "h": 1,
        "w": 24,
        "x": 0,
        "y": 22
      },
      "id": 2,
      "panels": [],
      "title": "Specific Threshold",
      "type": "row"
    },
    {
      "datasource": {
        "type": "elasticsearch",
        "uid": "P9C1AEFD5EC435EE7"
      },
      "description": "",
      "fieldConfig": {
        "defaults": {
          "color": {
            "mode": "thresholds"
          },
          "mappings": [],
          "thresholds": {
            "mode": "absolute",
            "steps": [
              {
                "color": "green"
              }
            ]
          },
          "unit": "decgbytes"
        },
        "overrides": []
      },
      "gridPos": {
        "h": 3,
        "w": 8,
        "x": 0,
        "y": 23
      },
      "id": 18,
      "options": {
        "colorMode": "value",
        "graphMode": "area",
        "justifyMode": "auto",
        "orientation": "auto",
        "reduceOptions": {
          "calcs": [
            "lastNotNull"
          ],
          "fields": "",
          "values": false
        },
        "showPercentChange": false,
        "textMode": "auto",
        "wideLayout": true
      },
      "pluginVersion": "10.4.1",
      "targets": [
        {
          "datasource": {
            "name": "Expression",
            "type": "__expr__",
            "uid": "__expr__"
          },
          "expression": "$specific_threshold_volume_produced",
          "hide": false,
          "refId": "B",
          "type": "math"
        }
      ],
      "title": "Volume Threshold PRIP $satellite_unit level : $stb_level timeliness : $stb_timeliness",
      "type": "stat"
    },
    {
      "datasource": {
        "type": "elasticsearch",
        "uid": "P9C1AEFD5EC435EE7"
      },
      "fieldConfig": {
        "defaults": {
          "color": {
            "mode": "thresholds"
          },
          "mappings": [],
          "thresholds": {
            "mode": "absolute",
            "steps": [
              {
                "color": "green"
              }
            ]
          },
          "unit": "decgbytes"
        },
        "overrides": []
      },
      "gridPos": {
        "h": 3,
        "w": 8,
        "x": 8,
        "y": 23
      },
      "id": 19,
      "options": {
        "colorMode": "value",
        "graphMode": "area",
        "justifyMode": "auto",
        "orientation": "auto",
        "reduceOptions": {
          "calcs": [
            "lastNotNull"
          ],
          "fields": "",
          "values": false
        },
        "showPercentChange": false,
        "textMode": "auto",
        "wideLayout": true
      },
      "pluginVersion": "10.4.1",
      "targets": [
        {
          "datasource": {
            "name": "Expression",
            "type": "__expr__",
            "uid": "__expr__"
          },
          "expression": "$specific_threshold_volume_archived",
          "hide": false,
          "refId": "A",
          "type": "math"
        }
      ],
      "title": "Volume Threshold LTA $satellite_unit level : $stb_level timeliness : $stb_timeliness provider:$lta_provider",
      "type": "stat"
    },
    {
      "datasource": {
        "type": "elasticsearch",
        "uid": "P9C1AEFD5EC435EE7"
      },
      "fieldConfig": {
        "defaults": {
          "color": {
            "mode": "thresholds"
          },
          "mappings": [],
          "thresholds": {
            "mode": "absolute",
            "steps": [
              {
                "color": "green"
              }
            ]
          },
          "unit": "decgbytes"
        },
        "overrides": []
      },
      "gridPos": {
        "h": 3,
        "w": 8,
        "x": 16,
        "y": 23
      },
      "id": 20,
      "options": {
        "colorMode": "value",
        "graphMode": "area",
        "justifyMode": "auto",
        "orientation": "auto",
        "reduceOptions": {
          "calcs": [
            "lastNotNull"
          ],
          "fields": "",
          "values": false
        },
        "showPercentChange": false,
        "textMode": "auto",
        "wideLayout": true
      },
      "pluginVersion": "10.4.1",
      "targets": [
        {
          "datasource": {
            "name": "Expression",
            "type": "__expr__",
            "uid": "__expr__"
          },
          "expression": "$specific_threshold_volume_disseminated",
          "hide": false,
          "refId": "C",
          "type": "math"
        }
      ],
      "title": "Volume Threshold Disseminated $satellite_unit level : $stb_level timeliness : $stb_timeliness",
      "type": "stat"
    },
    {
      "datasource": {
        "type": "elasticsearch",
        "uid": "P9C1AEFD5EC435EE7"
      },
      "fieldConfig": {
        "defaults": {
          "color": {
            "mode": "palette-classic"
          },
          "custom": {
            "axisBorderShow": false,
            "axisCenteredZero": false,
            "axisColorMode": "text",
            "axisGridShow": true,
            "axisLabel": "",
            "axisPlacement": "auto",
            "barAlignment": 0,
            "drawStyle": "line",
            "fillOpacity": 0,
            "gradientMode": "none",
            "hideFrom": {
              "legend": false,
              "tooltip": false,
              "viz": false
            },
            "insertNulls": false,
            "lineInterpolation": "linear",
            "lineWidth": 1,
            "pointSize": 5,
            "scaleDistribution": {
              "type": "linear"
            },
            "showPoints": "auto",
            "spanNulls": false,
            "stacking": {
              "group": "A",
              "mode": "none"
            },
            "thresholdsStyle": {
              "mode": "line"
            }
          },
          "mappings": [],
          "thresholds": {
            "mode": "absolute",
            "steps": [
              {
                "color": "green"
              }
            ]
          },
          "unit": "decgbytes"
        },
        "overrides": []
      },
      "gridPos": {
        "h": 9,
        "w": 8,
        "x": 0,
        "y": 26
      },
      "id": 11,
      "maxPerRow": 6,
      "options": {
        "legend": {
          "calcs": [],
          "displayMode": "list",
          "placement": "bottom",
          "showLegend": true
        },
        "tooltip": {
          "mode": "single",
          "sort": "none"
        }
      },
      "pluginVersion": "10.3.1",
      "repeatDirection": "h",
      "targets": [
        {
          "alias": "Volume In GB in database",
          "bucketAggs": [
            {
              "field": "sensing_start_date",
              "id": "2",
              "settings": {
                "interval": "1d"
              },
              "type": "date_histogram"
            }
          ],
          "datasource": {
            "type": "elasticsearch",
            "uid": "P9C1AEFD5EC435EE7"
          },
          "hide": false,
          "metrics": [
            {
              "field": "content_length",
              "id": "1",
              "settings": {
                "script": "_value / 1000000000"
              },
              "type": "sum"
            }
          ],
          "query": "mission:$mission AND satellite_unit:$satellite_unit AND service_type:PRIP AND product_type:${database_type:lucene} AND timeliness:${database_timeliness:lucene} ",
          "refId": "A",
          "timeField": "sensing_start_date"
        },
        {
          "datasource": {
            "name": "Expression",
            "type": "__expr__",
            "uid": "__expr__"
          },
          "expression": "$specific_threshold_volume_produced",
          "hide": false,
          "refId": "B",
          "type": "math"
        }
      ],
      "title": "Volume PRIP $satellite_unit level : $stb_level timeliness : $stb_timeliness",
      "transformations": [
        {
          "id": "configFromData",
          "options": {
            "configRefId": "B",
            "mappings": [
              {
                "fieldName": "B",
                "handlerKey": "threshold1"
              }
            ]
          }
        }
      ],
      "type": "timeseries"
    },
    {
      "datasource": {
        "type": "elasticsearch",
        "uid": "P9C1AEFD5EC435EE7"
      },
      "fieldConfig": {
        "defaults": {
          "color": {
            "mode": "palette-classic"
          },
          "custom": {
            "axisBorderShow": false,
            "axisCenteredZero": false,
            "axisColorMode": "text",
            "axisLabel": "",
            "axisPlacement": "auto",
            "barAlignment": 0,
            "drawStyle": "line",
            "fillOpacity": 0,
            "gradientMode": "none",
            "hideFrom": {
              "legend": false,
              "tooltip": false,
              "viz": false
            },
            "insertNulls": false,
            "lineInterpolation": "linear",
            "lineWidth": 1,
            "pointSize": 5,
            "scaleDistribution": {
              "type": "linear"
            },
            "showPoints": "auto",
            "spanNulls": false,
            "stacking": {
              "group": "A",
              "mode": "none"
            },
            "thresholdsStyle": {
              "mode": "line"
            }
          },
          "mappings": [],
          "thresholds": {
            "mode": "absolute",
            "steps": [
              {
                "color": "green"
              }
            ]
          },
          "unit": "decgbytes"
        },
        "overrides": []
      },
      "gridPos": {
        "h": 9,
        "w": 8,
        "x": 8,
        "y": 26
      },
      "id": 12,
      "maxPerRow": 6,
      "options": {
        "legend": {
          "calcs": [],
          "displayMode": "list",
          "placement": "bottom",
          "showLegend": true
        },
        "tooltip": {
          "mode": "single",
          "sort": "none"
        }
      },
      "pluginVersion": "10.3.1",
      "repeatDirection": "h",
      "targets": [
        {
          "alias": "Volume In GB in database",
          "bucketAggs": [
            {
              "field": "sensing_start_date",
              "id": "2",
              "settings": {
                "interval": "1d"
              },
              "type": "date_histogram"
            }
          ],
          "datasource": {
            "type": "elasticsearch",
            "uid": "P9C1AEFD5EC435EE7"
          },
          "hide": false,
          "metrics": [
            {
              "field": "content_length",
              "id": "1",
              "settings": {
                "script": "_value / 1000000000"
              },
              "type": "sum"
            }
          ],
          "query": "mission:$mission AND satellite_unit:$satellite_unit AND service_type:LTA AND service_id:$lta_provider AND product_type:${database_type:lucene} AND timeliness:${database_timeliness:lucene}",
          "refId": "A",
          "timeField": "sensing_start_date"
        },
        {
          "datasource": {
            "name": "Expression",
            "type": "__expr__",
            "uid": "__expr__"
          },
          "expression": "$specific_threshold_volume_archived",
          "hide": false,
          "refId": "B",
          "type": "math"
        }
      ],
      "title": "Volume LTA $satellite_unit level : $stb_level timeliness : $stb_timeliness provider:$lta_provider",
      "transformations": [
        {
          "id": "configFromData",
          "options": {
            "configRefId": "B",
            "mappings": [
              {
                "fieldName": "B",
                "handlerKey": "threshold1"
              }
            ]
          }
        }
      ],
      "type": "timeseries"
    },
    {
      "datasource": {
        "type": "elasticsearch",
        "uid": "P9C1AEFD5EC435EE7"
      },
      "fieldConfig": {
        "defaults": {
          "color": {
            "mode": "palette-classic"
          },
          "custom": {
            "axisBorderShow": false,
            "axisCenteredZero": false,
            "axisColorMode": "text",
            "axisLabel": "",
            "axisPlacement": "auto",
            "barAlignment": 0,
            "drawStyle": "line",
            "fillOpacity": 0,
            "gradientMode": "none",
            "hideFrom": {
              "legend": false,
              "tooltip": false,
              "viz": false
            },
            "insertNulls": false,
            "lineInterpolation": "linear",
            "lineWidth": 1,
            "pointSize": 5,
            "scaleDistribution": {
              "type": "linear"
            },
            "showPoints": "auto",
            "spanNulls": false,
            "stacking": {
              "group": "A",
              "mode": "none"
            },
            "thresholdsStyle": {
              "mode": "line"
            }
          },
          "mappings": [],
          "thresholds": {
            "mode": "absolute",
            "steps": [
              {
                "color": "green"
              }
            ]
          },
          "unit": "decgbytes"
        },
        "overrides": []
      },
      "gridPos": {
        "h": 9,
        "w": 8,
        "x": 16,
        "y": 26
      },
      "id": 13,
      "maxPerRow": 6,
      "options": {
        "legend": {
          "calcs": [],
          "displayMode": "list",
          "placement": "bottom",
          "showLegend": true
        },
        "tooltip": {
          "mode": "single",
          "sort": "none"
        }
      },
      "pluginVersion": "10.3.1",
      "repeatDirection": "h",
      "targets": [
        {
          "alias": "Volume In GB in database",
          "bucketAggs": [
            {
              "field": "sensing_start_date",
              "id": "2",
              "settings": {
                "interval": "1d"
              },
              "type": "date_histogram"
            }
          ],
          "datasource": {
            "type": "elasticsearch",
            "uid": "P9C1AEFD5EC435EE7"
          },
          "hide": false,
          "metrics": [
            {
              "field": "content_length",
              "id": "1",
              "settings": {
                "script": "_value / 1000000000"
              },
              "type": "sum"
            }
          ],
          "query": "mission:$mission AND satellite_unit:$satellite_unit AND service_type:DD AND product_type:${database_type:lucene} AND timeliness:${database_timeliness:lucene}",
          "refId": "A",
          "timeField": "sensing_start_date"
        },
        {
          "datasource": {
            "name": "Expression",
            "type": "__expr__",
            "uid": "__expr__"
          },
          "expression": "$specific_threshold_volume_disseminated",
          "hide": false,
          "refId": "B",
          "type": "math"
        }
      ],
      "title": "Volume Disseminated $satellite_unit level : $stb_level timeliness : $stb_timeliness",
      "transformations": [
        {
          "id": "configFromData",
          "options": {
            "configRefId": "B",
            "mappings": [
              {
                "fieldName": "B",
                "handlerKey": "threshold1"
              }
            ]
          }
        }
      ],
      "type": "timeseries"
    },
    {
      "datasource": {
        "type": "elasticsearch",
        "uid": "P9C1AEFD5EC435EE7"
      },
      "fieldConfig": {
        "defaults": {
          "color": {
            "mode": "thresholds"
          },
          "mappings": [],
          "thresholds": {
            "mode": "absolute",
            "steps": [
              {
                "color": "green"
              }
            ]
          },
          "unit": "none"
        },
        "overrides": []
      },
      "gridPos": {
        "h": 3,
        "w": 8,
        "x": 0,
        "y": 35
      },
      "id": 21,
      "options": {
        "colorMode": "value",
        "graphMode": "area",
        "justifyMode": "auto",
        "orientation": "auto",
        "reduceOptions": {
          "calcs": [
            "lastNotNull"
          ],
          "fields": "",
          "values": false
        },
        "showPercentChange": false,
        "textMode": "auto",
        "wideLayout": true
      },
      "pluginVersion": "10.4.1",
      "targets": [
        {
          "datasource": {
            "name": "Expression",
            "type": "__expr__",
            "uid": "__expr__"
          },
          "expression": "$specific_threshold_count_produced",
          "hide": false,
          "refId": "B",
          "type": "math"
        }
      ],
      "title": "Count Threshold PRIP $satellite_unit level : $stb_level timeliness : $stb_timeliness",
      "type": "stat"
    },
    {
      "datasource": {
        "type": "elasticsearch",
        "uid": "P9C1AEFD5EC435EE7"
      },
      "fieldConfig": {
        "defaults": {
          "color": {
            "mode": "thresholds"
          },
          "mappings": [],
          "thresholds": {
            "mode": "absolute",
            "steps": [
              {
                "color": "green"
              }
            ]
          },
          "unit": "none"
        },
        "overrides": []
      },
      "gridPos": {
        "h": 3,
        "w": 8,
        "x": 8,
        "y": 35
      },
      "id": 22,
      "options": {
        "colorMode": "value",
        "graphMode": "area",
        "justifyMode": "auto",
        "orientation": "auto",
        "reduceOptions": {
          "calcs": [
            "lastNotNull"
          ],
          "fields": "",
          "values": false
        },
        "showPercentChange": false,
        "textMode": "auto",
        "wideLayout": true
      },
      "pluginVersion": "10.4.1",
      "targets": [
        {
          "datasource": {
            "name": "Expression",
            "type": "__expr__",
            "uid": "__expr__"
          },
          "expression": "$specific_threshold_count_archived",
          "hide": false,
          "refId": "B",
          "type": "math"
        }
      ],
      "title": "Count Threshold LTA $satellite_unit level : $stb_level timeliness : $stb_timeliness provider:$lta_provider",
      "type": "stat"
    },
    {
      "datasource": {
        "type": "elasticsearch",
        "uid": "P9C1AEFD5EC435EE7"
      },
      "fieldConfig": {
        "defaults": {
          "color": {
            "mode": "thresholds"
          },
          "mappings": [],
          "thresholds": {
            "mode": "absolute",
            "steps": [
              {
                "color": "green"
              }
            ]
          },
          "unit": "none"
        },
        "overrides": []
      },
      "gridPos": {
        "h": 3,
        "w": 8,
        "x": 16,
        "y": 35
      },
      "id": 23,
      "options": {
        "colorMode": "value",
        "graphMode": "area",
        "justifyMode": "auto",
        "orientation": "auto",
        "reduceOptions": {
          "calcs": [
            "lastNotNull"
          ],
          "fields": "",
          "values": false
        },
        "showPercentChange": false,
        "textMode": "auto",
        "wideLayout": true
      },
      "pluginVersion": "10.4.1",
      "targets": [
        {
          "datasource": {
            "name": "Expression",
            "type": "__expr__",
            "uid": "__expr__"
          },
          "expression": "$specific_threshold_count_disseminated",
          "hide": false,
          "refId": "B",
          "type": "math"
        }
      ],
      "title": "Count Threshold Disseminated $satellite_unit level : $stb_level timeliness : $stb_timeliness",
      "type": "stat"
    },
    {
      "datasource": {
        "type": "elasticsearch",
        "uid": "P9C1AEFD5EC435EE7"
      },
      "fieldConfig": {
        "defaults": {
          "color": {
            "mode": "palette-classic"
          },
          "custom": {
            "axisBorderShow": false,
            "axisCenteredZero": false,
            "axisColorMode": "text",
            "axisLabel": "",
            "axisPlacement": "auto",
            "barAlignment": 0,
            "drawStyle": "line",
            "fillOpacity": 0,
            "gradientMode": "none",
            "hideFrom": {
              "legend": false,
              "tooltip": false,
              "viz": false
            },
            "insertNulls": false,
            "lineInterpolation": "linear",
            "lineWidth": 1,
            "pointSize": 5,
            "scaleDistribution": {
              "type": "linear"
            },
            "showPoints": "auto",
            "spanNulls": false,
            "stacking": {
              "group": "A",
              "mode": "none"
            },
            "thresholdsStyle": {
              "mode": "line"
            }
          },
          "mappings": [],
          "thresholds": {
            "mode": "absolute",
            "steps": [
              {
                "color": "green"
              }
            ]
          },
          "unit": "none"
        },
        "overrides": []
      },
      "gridPos": {
        "h": 9,
        "w": 8,
        "x": 0,
        "y": 38
      },
      "id": 14,
      "maxPerRow": 6,
      "options": {
        "legend": {
          "calcs": [],
          "displayMode": "list",
          "placement": "bottom",
          "showLegend": true
        },
        "tooltip": {
          "mode": "single",
          "sort": "none"
        }
      },
      "pluginVersion": "10.3.1",
      "repeatDirection": "h",
      "targets": [
        {
          "alias": "Number of document in database",
          "bucketAggs": [
            {
              "field": "sensing_start_date",
              "id": "2",
              "settings": {
                "interval": "1d"
              },
              "type": "date_histogram"
            }
          ],
          "datasource": {
            "type": "elasticsearch",
            "uid": "P9C1AEFD5EC435EE7"
          },
          "hide": false,
          "metrics": [
            {
              "id": "1",
              "type": "count"
            }
          ],
          "query": "mission:$mission AND satellite_unit:$satellite_unit AND service_type:PRIP AND product_type:${database_type:lucene} AND timeliness:${database_timeliness:lucene}",
          "refId": "A",
          "timeField": "sensing_start_date"
        },
        {
          "datasource": {
            "name": "Expression",
            "type": "__expr__",
            "uid": "__expr__"
          },
          "expression": "$specific_threshold_count_produced",
          "hide": false,
          "refId": "B",
          "type": "math"
        }
      ],
      "title": "Count PRIP $satellite_unit level : $stb_level timeliness : $stb_timeliness",
      "transformations": [
        {
          "id": "configFromData",
          "options": {
            "configRefId": "B",
            "mappings": [
              {
                "fieldName": "B",
                "handlerKey": "threshold1"
              }
            ]
          }
        }
      ],
      "type": "timeseries"
    },
    {
      "datasource": {
        "type": "elasticsearch",
        "uid": "P9C1AEFD5EC435EE7"
      },
      "fieldConfig": {
        "defaults": {
          "color": {
            "mode": "palette-classic"
          },
          "custom": {
            "axisBorderShow": false,
            "axisCenteredZero": false,
            "axisColorMode": "text",
            "axisLabel": "",
            "axisPlacement": "auto",
            "barAlignment": 0,
            "drawStyle": "line",
            "fillOpacity": 0,
            "gradientMode": "none",
            "hideFrom": {
              "legend": false,
              "tooltip": false,
              "viz": false
            },
            "insertNulls": false,
            "lineInterpolation": "linear",
            "lineWidth": 1,
            "pointSize": 5,
            "scaleDistribution": {
              "type": "linear"
            },
            "showPoints": "auto",
            "spanNulls": false,
            "stacking": {
              "group": "A",
              "mode": "none"
            },
            "thresholdsStyle": {
              "mode": "line"
            }
          },
          "mappings": [],
          "thresholds": {
            "mode": "absolute",
            "steps": [
              {
                "color": "green"
              }
            ]
          },
          "unit": "none"
        },
        "overrides": []
      },
      "gridPos": {
        "h": 9,
        "w": 8,
        "x": 8,
        "y": 38
      },
      "id": 17,
      "maxPerRow": 6,
      "options": {
        "legend": {
          "calcs": [],
          "displayMode": "list",
          "placement": "bottom",
          "showLegend": true
        },
        "tooltip": {
          "mode": "single",
          "sort": "none"
        }
      },
      "pluginVersion": "10.3.1",
      "repeatDirection": "h",
      "targets": [
        {
          "alias": "Number of document in database",
          "bucketAggs": [
            {
              "field": "sensing_start_date",
              "id": "2",
              "settings": {
                "interval": "1d"
              },
              "type": "date_histogram"
            }
          ],
          "datasource": {
            "type": "elasticsearch",
            "uid": "P9C1AEFD5EC435EE7"
          },
          "hide": false,
          "metrics": [
            {
              "id": "1",
              "type": "count"
            }
          ],
          "query": "mission:$mission AND satellite_unit:$satellite_unit AND service_type:LTA AND service_id:$lta_provider AND product_type:${database_type:lucene} AND timeliness:${database_timeliness:lucene}",
          "refId": "A",
          "timeField": "sensing_start_date"
        },
        {
          "datasource": {
            "name": "Expression",
            "type": "__expr__",
            "uid": "__expr__"
          },
          "expression": "$specific_threshold_count_archived",
          "hide": false,
          "refId": "B",
          "type": "math"
        }
      ],
      "title": "Count LTA $satellite_unit level : $stb_level timeliness : $stb_timeliness provider:$lta_provider",
      "transformations": [
        {
          "id": "configFromData",
          "options": {
            "configRefId": "B",
            "mappings": [
              {
                "fieldName": "B",
                "handlerKey": "threshold1"
              }
            ]
          }
        }
      ],
      "type": "timeseries"
    },
    {
      "datasource": {
        "type": "elasticsearch",
        "uid": "P9C1AEFD5EC435EE7"
      },
      "fieldConfig": {
        "defaults": {
          "color": {
            "mode": "palette-classic"
          },
          "custom": {
            "axisBorderShow": false,
            "axisCenteredZero": false,
            "axisColorMode": "text",
            "axisLabel": "",
            "axisPlacement": "auto",
            "barAlignment": 0,
            "drawStyle": "line",
            "fillOpacity": 0,
            "gradientMode": "none",
            "hideFrom": {
              "legend": false,
              "tooltip": false,
              "viz": false
            },
            "insertNulls": false,
            "lineInterpolation": "linear",
            "lineWidth": 1,
            "pointSize": 5,
            "scaleDistribution": {
              "type": "linear"
            },
            "showPoints": "auto",
            "spanNulls": false,
            "stacking": {
              "group": "A",
              "mode": "none"
            },
            "thresholdsStyle": {
              "mode": "line"
            }
          },
          "mappings": [],
          "thresholds": {
            "mode": "absolute",
            "steps": [
              {
                "color": "green"
              }
            ]
          },
          "unit": "none"
        },
        "overrides": []
      },
      "gridPos": {
        "h": 9,
        "w": 8,
        "x": 16,
        "y": 38
      },
      "id": 16,
      "maxPerRow": 6,
      "options": {
        "legend": {
          "calcs": [],
          "displayMode": "list",
          "placement": "bottom",
          "showLegend": true
        },
        "tooltip": {
          "mode": "single",
          "sort": "none"
        }
      },
      "pluginVersion": "10.3.1",
      "repeatDirection": "h",
      "targets": [
        {
          "alias": "Number of document in database",
          "bucketAggs": [
            {
              "field": "sensing_start_date",
              "id": "2",
              "settings": {
                "interval": "1d"
              },
              "type": "date_histogram"
            }
          ],
          "datasource": {
            "type": "elasticsearch",
            "uid": "P9C1AEFD5EC435EE7"
          },
          "hide": false,
          "metrics": [
            {
              "id": "1",
              "type": "count"
            }
          ],
          "query": "mission:$mission AND satellite_unit:$satellite_unit AND service_type:DD AND product_type:${database_type:lucene} AND timeliness:${database_timeliness:lucene}",
          "refId": "A",
          "timeField": "sensing_start_date"
        },
        {
          "datasource": {
            "name": "Expression",
            "type": "__expr__",
            "uid": "__expr__"
          },
          "expression": "$specific_threshold_count_disseminated",
          "hide": false,
          "refId": "B",
          "type": "math"
        }
      ],
      "title": "Count Disseminated $satellite_unit level : $stb_level timeliness : $stb_timeliness",
      "transformations": [
        {
          "id": "configFromData",
          "options": {
            "configRefId": "B",
            "mappings": [
              {
                "fieldName": "B",
                "handlerKey": "threshold1"
              }
            ]
          }
        }
      ],
      "type": "timeseries"
    }
  ],
  "refresh": "",
  "schemaVersion": 39,
  "tags": [
    "System Technical budget"
  ],
  "templating": {
    "list": [
      {
        "allValue": "",
        "current": {
          "selected": true,
          "text": [
            "1.8"
          ],
          "value": [
            "1.8"
          ]
        },
        "datasource": {
          "type": "yesoreyeram-infinity-datasource",
          "uid": "PD0067CAD9A63E081"
        },
        "definition": "Infinity- (infinity) json",
        "description": "",
        "hide": 0,
        "includeAll": false,
        "label": "Version",
        "multi": true,
        "name": "version",
        "options": [],
        "query": {
          "infinityQuery": {
            "columns": [
              {
                "selector": "_source.version",
                "text": "type",
                "type": "string"
              }
            ],
            "filters": [],
            "format": "table",
            "pagination_mode": "none",
            "parser": "backend",
            "refId": "variable",
            "root_selector": "hits.hits",
            "source": "url",
            "summarizeExpression": "",
            "type": "json",
            "url": "/cds-databudget-conf/_search?q=version:*&size=10000",
            "url_options": {
              "data": "",
              "method": "GET"
            }
          },
          "query": "",
          "queryType": "infinity"
        },
        "refresh": 2,
        "regex": "",
        "skipUrlSync": false,
        "sort": 0,
        "type": "query"
      },
      {
        "current": {
          "selected": false,
          "text": "S1",
          "value": "S1"
        },
        "hide": 0,
        "includeAll": false,
        "label": "Mission",
        "multi": false,
        "name": "mission",
        "options": [
          {
            "selected": true,
            "text": "S1",
            "value": "S1"
          },
          {
            "selected": false,
            "text": "S2",
            "value": "S2"
          },
          {
            "selected": false,
            "text": "S3",
            "value": "S3"
          },
          {
            "selected": false,
            "text": "S5",
            "value": "S5"
          }
        ],
        "query": "S1,S2,S3,S5",
        "queryValue": "",
        "skipUrlSync": false,
        "type": "custom"
      },
      {
        "current": {
          "selected": false,
          "text": "S1A",
          "value": "S1A"
        },
        "datasource": {
          "type": "elasticsearch",
          "uid": "P9C1AEFD5EC435EE7"
        },
        "definition": "{\"find\":\"terms\",\"field\":\"satellite_unit\", \"query\":\"mission: $mission\"}",
        "hide": 0,
        "includeAll": false,
        "label": "Satellite Unit",
        "multi": false,
        "name": "satellite_unit",
        "options": [],
        "query": "{\"find\":\"terms\",\"field\":\"satellite_unit\", \"query\":\"mission: $mission\"}",
        "refresh": 2,
        "regex": "",
        "skipUrlSync": false,
        "sort": 0,
        "type": "query"
      },
      {
        "current": {
          "selected": false,
          "text": "L0",
          "value": "L0"
        },
        "datasource": {
          "type": "yesoreyeram-infinity-datasource",
          "uid": "PD0067CAD9A63E081"
        },
        "definition": "Infinity- (infinity) json",
        "hide": 0,
        "includeAll": false,
        "label": "STB Level",
        "multi": false,
        "name": "stb_level",
        "options": [],
        "query": {
          "infinityQuery": {
            "columns": [
              {
                "selector": "_source.level",
                "text": "level",
                "type": "string"
              }
            ],
            "filters": [],
            "format": "table",
            "parser": "backend",
            "refId": "variable",
            "root_selector": "hits.hits",
            "source": "url",
            "summarizeExpression": "",
            "type": "json",
            "url": "/cds-databudget-conf/_search?q=version:$version AND mission:$mission AND data_category:RAW&size=1000",
            "url_options": {
              "data": "",
              "method": "GET"
            }
          },
          "query": "",
          "queryType": "infinity"
        },
        "refresh": 2,
        "regex": "",
        "skipUrlSync": false,
        "sort": 0,
        "type": "query"
      },
      {
        "current": {
          "selected": false,
          "text": "NRT",
          "value": "NRT"
        },
        "datasource": {
          "type": "yesoreyeram-infinity-datasource",
          "uid": "PD0067CAD9A63E081"
        },
        "definition": "Infinity- (infinity) json",
        "hide": 0,
        "includeAll": false,
        "label": "STB Timeliness",
        "multi": false,
        "name": "stb_timeliness",
        "options": [],
        "query": {
          "infinityQuery": {
            "columns": [
              {
                "selector": "_source.timeliness",
                "text": "level",
                "type": "string"
              }
            ],
            "filters": [],
            "format": "table",
            "parser": "backend",
            "refId": "variable",
            "root_selector": "hits.hits",
            "source": "url",
            "summarizeExpression": "",
            "type": "json",
            "url": "/cds-databudget-conf/_search?q=version:$version AND mission:$mission AND data_category:RAW AND level:$stb_level&size=1000",
            "url_options": {
              "data": "",
              "method": "GET"
            }
          },
          "query": "",
          "queryType": "infinity"
        },
        "refresh": 2,
        "regex": "",
        "skipUrlSync": false,
        "sort": 0,
        "type": "query"
      },
      {
        "current": {
          "selected": false,
          "text": "Werum",
          "value": "Werum"
        },
        "datasource": {
          "type": "elasticsearch",
          "uid": "P9C1AEFD5EC435EE7"
        },
        "definition": "{\"find\":\"terms\",\"field\":\"service_id\", \"query\":\"mission: $mission AND service_type:LTA\"}",
        "hide": 0,
        "includeAll": false,
        "label": "LTA",
        "multi": false,
        "name": "lta_provider",
        "options": [],
        "query": "{\"find\":\"terms\",\"field\":\"service_id\", \"query\":\"mission: $mission AND service_type:LTA\"}",
        "refresh": 2,
        "regex": "",
        "skipUrlSync": false,
        "sort": 0,
        "type": "query"
      },
      {
        "current": {
          "selected": false,
          "text": "4215.2202",
          "value": "4215.2202"
        },
        "datasource": {
          "type": "yesoreyeram-infinity-datasource",
          "uid": "PD0067CAD9A63E081"
        },
        "definition": "Infinity- (infinity) json",
        "hide": 2,
        "includeAll": false,
        "multi": false,
        "name": "global_threshold_volume_produced",
        "options": [],
        "query": {
          "infinityQuery": {
            "columns": [
              {
                "selector": "_source.threshold_volume",
                "text": "Volume",
                "type": "number"
              }
            ],
            "filters": [],
            "format": "table",
            "parser": "backend",
            "refId": "variable",
            "root_selector": "hits.hits",
            "source": "url",
            "summarizeExpression": "sum(Volume)",
            "type": "json",
            "url": "/cds-databudget-conf/_search?q=version:$version AND mission:$mission AND data_category:GLOBAL_THRESHOLD AND threshold_subtype:produced&size=1000",
            "url_options": {
              "data": "",
              "method": "GET"
            }
          },
          "query": "",
          "queryType": "infinity"
        },
        "refresh": 2,
        "regex": "",
        "skipUrlSync": false,
        "sort": 0,
        "type": "query"
      },
      {
        "current": {
          "selected": false,
          "text": "1084.8723000000005",
          "value": "1084.8723000000005"
        },
        "datasource": {
          "type": "yesoreyeram-infinity-datasource",
          "uid": "PD0067CAD9A63E081"
        },
        "definition": "Infinity- (infinity) json",
        "hide": 2,
        "includeAll": false,
        "multi": false,
        "name": "global_threshold_volume_archived",
        "options": [],
        "query": {
          "infinityQuery": {
            "columns": [
              {
                "selector": "_source.threshold_volume",
                "text": "Volume",
                "type": "number"
              }
            ],
            "filters": [],
            "format": "table",
            "parser": "backend",
            "refId": "variable",
            "root_selector": "hits.hits",
            "source": "url",
            "summarizeExpression": "sum(Volume)",
            "type": "json",
            "url": "/cds-databudget-conf/_search?q=version:$version AND mission:$mission AND data_category:GLOBAL_THRESHOLD AND threshold_subtype:archived&size=1000",
            "url_options": {
              "data": "",
              "method": "GET"
            }
          },
          "query": "",
          "queryType": "infinity"
        },
        "refresh": 2,
        "regex": "",
        "skipUrlSync": false,
        "sort": 0,
        "type": "query"
      },
      {
        "current": {
          "selected": false,
          "text": "4215.2202",
          "value": "4215.2202"
        },
        "datasource": {
          "type": "yesoreyeram-infinity-datasource",
          "uid": "PD0067CAD9A63E081"
        },
        "definition": "Infinity- (infinity) json",
        "hide": 2,
        "includeAll": false,
        "multi": false,
        "name": "global_threshold_volume_disseminated",
        "options": [],
        "query": {
          "infinityQuery": {
            "columns": [
              {
                "selector": "_source.threshold_volume",
                "text": "Volume",
                "type": "number"
              }
            ],
            "filters": [],
            "format": "table",
            "parser": "backend",
            "refId": "variable",
            "root_selector": "hits.hits",
            "source": "url",
            "summarizeExpression": "sum(Volume)",
            "type": "json",
            "url": "/cds-databudget-conf/_search?q=version:$version AND mission:$mission AND data_category:GLOBAL_THRESHOLD AND threshold_subtype:disseminated&size=1000",
            "url_options": {
              "data": "",
              "method": "GET"
            }
          },
          "query": "",
          "queryType": "infinity"
        },
        "refresh": 2,
        "regex": "",
        "skipUrlSync": false,
        "sort": 0,
        "type": "query"
      },
      {
        "current": {
          "selected": false,
          "text": "4558.120000000001",
          "value": "4558.120000000001"
        },
        "datasource": {
          "type": "yesoreyeram-infinity-datasource",
          "uid": "PD0067CAD9A63E081"
        },
        "definition": "Infinity- (infinity) json",
        "hide": 2,
        "includeAll": false,
        "multi": false,
        "name": "global_threshold_count_produced",
        "options": [],
        "query": {
          "infinityQuery": {
            "columns": [
              {
                "selector": "_source.threshold_count",
                "text": "Volume",
                "type": "number"
              }
            ],
            "filters": [],
            "format": "table",
            "parser": "backend",
            "refId": "variable",
            "root_selector": "hits.hits",
            "source": "url",
            "summarizeExpression": "sum(Volume)",
            "type": "json",
            "url": "/cds-databudget-conf/_search?q=version:$version AND mission:$mission AND data_category:GLOBAL_THRESHOLD AND threshold_subtype:produced&size=1000",
            "url_options": {
              "data": "",
              "method": "GET"
            }
          },
          "query": "",
          "queryType": "infinity"
        },
        "refresh": 2,
        "regex": "",
        "skipUrlSync": false,
        "sort": 0,
        "type": "query"
      },
      {
        "current": {
          "selected": false,
          "text": "1596.02",
          "value": "1596.02"
        },
        "datasource": {
          "type": "yesoreyeram-infinity-datasource",
          "uid": "PD0067CAD9A63E081"
        },
        "definition": "Infinity- (infinity) json",
        "hide": 2,
        "includeAll": false,
        "multi": false,
        "name": "global_threshold_count_archived",
        "options": [],
        "query": {
          "infinityQuery": {
            "columns": [
              {
                "selector": "_source.threshold_count",
                "text": "Volume",
                "type": "number"
              }
            ],
            "filters": [],
            "format": "table",
            "parser": "backend",
            "refId": "variable",
            "root_selector": "hits.hits",
            "source": "url",
            "summarizeExpression": "sum(Volume)",
            "type": "json",
            "url": "/cds-databudget-conf/_search?q=version:$version AND mission:$mission AND data_category:GLOBAL_THRESHOLD AND threshold_subtype:archived&size=1000",
            "url_options": {
              "data": "",
              "method": "GET"
            }
          },
          "query": "",
          "queryType": "infinity"
        },
        "refresh": 2,
        "regex": "",
        "skipUrlSync": false,
        "sort": 0,
        "type": "query"
      },
      {
        "current": {
          "selected": false,
          "text": "4502.02",
          "value": "4502.02"
        },
        "datasource": {
          "type": "yesoreyeram-infinity-datasource",
          "uid": "PD0067CAD9A63E081"
        },
        "definition": "Infinity- (infinity) json",
        "hide": 2,
        "includeAll": false,
        "multi": false,
        "name": "global_threshold_count_disseminated",
        "options": [],
        "query": {
          "infinityQuery": {
            "columns": [
              {
                "selector": "_source.threshold_count",
                "text": "Volume",
                "type": "number"
              }
            ],
            "filters": [],
            "format": "table",
            "parser": "backend",
            "refId": "variable",
            "root_selector": "hits.hits",
            "source": "url",
            "summarizeExpression": "sum(Volume)",
            "type": "json",
            "url": "/cds-databudget-conf/_search?q=version:$version AND mission:$mission AND data_category:GLOBAL_THRESHOLD AND threshold_subtype:disseminated&size=1000",
            "url_options": {
              "data": "",
              "method": "GET"
            }
          },
          "query": "",
          "queryType": "infinity"
        },
        "refresh": 2,
        "regex": "",
        "skipUrlSync": false,
        "sort": 0,
        "type": "query"
      },
      {
        "current": {
          "selected": false,
          "text": "275.978",
          "value": "275.978"
        },
        "datasource": {
          "type": "yesoreyeram-infinity-datasource",
          "uid": "PD0067CAD9A63E081"
        },
        "definition": "Infinity- (infinity) json",
        "hide": 2,
        "includeAll": false,
        "multi": false,
        "name": "specific_threshold_volume_disseminated",
        "options": [],
        "query": {
          "infinityQuery": {
            "columns": [
              {
                "selector": "_source.threshold_volume",
                "text": "Volume",
                "type": "number"
              }
            ],
            "filters": [],
            "format": "table",
            "parser": "backend",
            "refId": "variable",
            "root_selector": "hits.hits",
            "source": "url",
            "summarizeExpression": "sum(Volume)",
            "type": "json",
            "url": "/cds-databudget-conf/_search?q=version:$version AND mission:$mission AND level:$stb_level AND timeliness:$stb_timeliness AND data_category:SPECIFIC_THRESHOLD AND threshold_subtype:disseminated&size=1000",
            "url_options": {
              "data": "",
              "method": "GET"
            }
          },
          "query": "",
          "queryType": "infinity"
        },
        "refresh": 2,
        "regex": "",
        "skipUrlSync": false,
        "sort": 0,
        "type": "query"
      },
      {
        "current": {
          "selected": false,
          "text": "275.978",
          "value": "275.978"
        },
        "datasource": {
          "type": "yesoreyeram-infinity-datasource",
          "uid": "PD0067CAD9A63E081"
        },
        "definition": "Infinity- (infinity) json",
        "hide": 2,
        "includeAll": false,
        "multi": false,
        "name": "specific_threshold_volume_produced",
        "options": [],
        "query": {
          "infinityQuery": {
            "columns": [
              {
                "selector": "_source.threshold_volume",
                "text": "Volume",
                "type": "number"
              }
            ],
            "filters": [],
            "format": "table",
            "parser": "backend",
            "refId": "variable",
            "root_selector": "hits.hits",
            "source": "url",
            "summarizeExpression": "sum(Volume)",
            "type": "json",
            "url": "/cds-databudget-conf/_search?q=version:$version AND mission:$mission AND level:$stb_level AND timeliness:$stb_timeliness AND data_category:SPECIFIC_THRESHOLD AND threshold_subtype:produced&size=1000",
            "url_options": {
              "data": "",
              "method": "GET"
            }
          },
          "query": "",
          "queryType": "infinity"
        },
        "refresh": 2,
        "regex": "",
        "skipUrlSync": false,
        "sort": 0,
        "type": "query"
      },
      {
        "allValue": "0",
        "current": {
          "selected": true,
          "text": [
            "275.978"
          ],
          "value": [
            "275.978"
          ]
        },
        "datasource": {
          "type": "yesoreyeram-infinity-datasource",
          "uid": "PD0067CAD9A63E081"
        },
        "definition": "Infinity- (infinity) json",
        "hide": 2,
        "includeAll": false,
        "multi": true,
        "name": "specific_threshold_volume_archived",
        "options": [],
        "query": {
          "infinityQuery": {
            "columns": [
              {
                "selector": "_source.threshold_volume",
                "text": "Volume",
                "type": "number"
              }
            ],
            "computed_columns": [
              {
                "selector": "",
                "text": "",
                "type": "string"
              }
            ],
            "filters": [],
            "format": "table",
            "parser": "backend",
            "refId": "variable",
            "root_selector": "hits.hits",
            "source": "url",
            "summarizeExpression": "sum(Volume)",
            "type": "json",
            "url": "/cds-databudget-conf/_search?q=version:$version AND mission:$mission AND level:$stb_level AND timeliness:$stb_timeliness AND data_category:SPECIFIC_THRESHOLD AND threshold_subtype:archived&size=1000",
            "url_options": {
              "data": "",
              "method": "GET"
            }
          },
          "query": "",
          "queryType": "infinity"
        },
        "refresh": 2,
        "regex": "",
        "skipUrlSync": false,
        "sort": 0,
        "type": "query"
      },
      {
        "current": {
          "selected": false,
          "text": "218.04999999999998",
          "value": "218.04999999999998"
        },
        "datasource": {
          "type": "yesoreyeram-infinity-datasource",
          "uid": "PD0067CAD9A63E081"
        },
        "definition": "Infinity- (infinity) json",
        "hide": 2,
        "includeAll": false,
        "multi": false,
        "name": "specific_threshold_count_disseminated",
        "options": [],
        "query": {
          "infinityQuery": {
            "columns": [
              {
                "selector": "_source.threshold_count",
                "text": "Count",
                "type": "number"
              }
            ],
            "filters": [],
            "format": "table",
            "parser": "backend",
            "refId": "variable",
            "root_selector": "hits.hits",
            "source": "url",
            "summarizeExpression": "sum(Count)",
            "type": "json",
            "url": "/cds-databudget-conf/_search?q=version:$version AND mission:$mission AND level:$stb_level AND timeliness:$stb_timeliness AND data_category:SPECIFIC_THRESHOLD AND threshold_subtype:disseminated&size=1000",
            "url_options": {
              "data": "",
              "method": "GET"
            }
          },
          "query": "",
          "queryType": "infinity"
        },
        "refresh": 2,
        "regex": "",
        "skipUrlSync": false,
        "sort": 0,
        "type": "query"
      },
      {
        "current": {
          "selected": false,
          "text": "218.04999999999998",
          "value": "218.04999999999998"
        },
        "datasource": {
          "type": "yesoreyeram-infinity-datasource",
          "uid": "PD0067CAD9A63E081"
        },
        "definition": "Infinity- (infinity) json",
        "hide": 2,
        "includeAll": false,
        "multi": false,
        "name": "specific_threshold_count_produced",
        "options": [],
        "query": {
          "infinityQuery": {
            "columns": [
              {
                "selector": "_source.threshold_count",
                "text": "Count",
                "type": "number"
              }
            ],
            "filters": [],
            "format": "table",
            "parser": "backend",
            "refId": "variable",
            "root_selector": "hits.hits",
            "source": "url",
            "summarizeExpression": "sum(Count)",
            "type": "json",
            "url": "/cds-databudget-conf/_search?q=version:$version AND mission:$mission AND level:$stb_level AND timeliness:$stb_timeliness AND data_category:SPECIFIC_THRESHOLD AND threshold_subtype:produced&size=1000",
            "url_options": {
              "data": "",
              "method": "GET"
            }
          },
          "query": "",
          "queryType": "infinity"
        },
        "refresh": 2,
        "regex": "",
        "skipUrlSync": false,
        "sort": 0,
        "type": "query"
      },
      {
        "current": {
          "selected": false,
          "text": "218.04999999999998",
          "value": "218.04999999999998"
        },
        "datasource": {
          "type": "yesoreyeram-infinity-datasource",
          "uid": "PD0067CAD9A63E081"
        },
        "definition": "Infinity- (infinity) json",
        "hide": 2,
        "includeAll": false,
        "multi": false,
        "name": "specific_threshold_count_archived",
        "options": [],
        "query": {
          "infinityQuery": {
            "columns": [
              {
                "selector": "_source.threshold_count",
                "text": "Count",
                "type": "number"
              }
            ],
            "filters": [],
            "format": "table",
            "parser": "backend",
            "refId": "variable",
            "root_selector": "hits.hits",
            "source": "url",
            "summarizeExpression": "sum(Count)",
            "type": "json",
            "url": "/cds-databudget-conf/_search?q=version:$version AND mission:$mission AND level:$stb_level AND timeliness:$stb_timeliness AND data_category:SPECIFIC_THRESHOLD AND threshold_subtype:archived&size=1000",
            "url_options": {
              "data": "",
              "method": "GET"
            }
          },
          "query": "",
          "queryType": "infinity"
        },
        "refresh": 2,
        "regex": "",
        "skipUrlSync": false,
        "sort": 0,
        "type": "query"
      },
      {
        "current": {
          "selected": true,
          "text": [
            "All"
          ],
          "value": [
            "$__all"
          ]
        },
        "datasource": {
          "type": "yesoreyeram-infinity-datasource",
          "uid": "PD0067CAD9A63E081"
        },
        "definition": "Infinity- (infinity) json",
        "description": "",
        "hide": 2,
        "includeAll": true,
        "multi": true,
        "name": "database_type",
        "options": [],
        "query": {
          "infinityQuery": {
            "columns": [
              {
                "selector": "_source.database_type",
                "text": "database_type",
                "type": "string"
              }
            ],
            "filters": [],
            "format": "table",
            "json_options": {
              "columnar": false
            },
            "parser": "backend",
            "refId": "variable",
            "root_selector": "hits.hits",
            "source": "url",
            "summarizeExpression": "",
            "type": "json",
            "url": "/cds-databudget-conf/_search?q=version:$version AND mission:$mission AND level:$stb_level AND timeliness:${stb_timeliness} AND data_category:RAW&size=10000",
            "url_options": {
              "data": "",
              "method": "GET",
              "params": []
            }
          },
          "query": "",
          "queryType": "infinity"
        },
        "refresh": 2,
        "regex": "",
        "skipUrlSync": false,
        "sort": 0,
        "type": "query"
      },
      {
        "allValue": "",
        "current": {
          "selected": true,
          "text": [
            "All"
          ],
          "value": [
            "$__all"
          ]
        },
        "datasource": {
          "type": "yesoreyeram-infinity-datasource",
          "uid": "PD0067CAD9A63E081"
        },
        "definition": "Infinity- (infinity) json",
        "description": "",
        "hide": 2,
        "includeAll": true,
        "multi": true,
        "name": "database_timeliness",
        "options": [],
        "query": {
          "infinityQuery": {
            "columns": [
              {
                "selector": "_source.database_timeliness",
                "text": "type",
                "type": "string"
              }
            ],
            "filters": [],
            "format": "table",
            "pagination_mode": "none",
            "parser": "backend",
            "refId": "variable",
            "root_selector": "hits.hits",
            "source": "url",
            "summarizeExpression": "",
            "type": "json",
            "url": "/cds-databudget-conf/_search?q=version:$version AND mission:$mission AND timeliness:$stb_timeliness AND data_category:TIMELINESS_LUT&size=10000",
            "url_options": {
              "data": "",
              "method": "GET"
            }
          },
          "query": "",
          "queryType": "infinity"
        },
        "refresh": 2,
        "regex": "",
        "skipUrlSync": false,
        "sort": 0,
        "type": "query"
      },
      {
        "allValue": "",
        "current": {
          "selected": true,
          "text": [
            "All"
          ],
          "value": [
            "$__all"
          ]
        },
        "datasource": {
          "type": "yesoreyeram-infinity-datasource",
          "uid": "PD0067CAD9A63E081"
        },
        "definition": "Infinity- (infinity) json",
        "description": "",
        "hide": 2,
        "includeAll": true,
        "multi": true,
        "name": "global_type_produced",
        "options": [],
        "query": {
          "infinityQuery": {
            "columns": [
              {
                "selector": "_source.database_type",
                "text": "type",
                "type": "string"
              }
            ],
            "filters": [],
            "format": "table",
            "pagination_mode": "none",
            "parser": "backend",
            "refId": "variable",
            "root_selector": "hits.hits",
            "source": "url",
            "summarizeExpression": "",
            "type": "json",
            "url": "/cds-databudget-conf/_search?q=version:$version AND mission:$mission AND produced:* AND data_category:RAW&size=10000",
            "url_options": {
              "data": "",
              "method": "GET"
            }
          },
          "query": "",
          "queryType": "infinity"
        },
        "refresh": 2,
        "regex": "",
        "skipUrlSync": false,
        "sort": 0,
        "type": "query"
      },
      {
        "allValue": "",
        "current": {
          "selected": true,
          "text": [
            "All"
          ],
          "value": [
            "$__all"
          ]
        },
        "datasource": {
          "type": "yesoreyeram-infinity-datasource",
          "uid": "PD0067CAD9A63E081"
        },
        "definition": "Infinity- (infinity) json",
        "description": "",
        "hide": 2,
        "includeAll": true,
        "multi": true,
        "name": "global_type_archived",
        "options": [],
        "query": {
          "infinityQuery": {
            "columns": [
              {
                "selector": "_source.database_type",
                "text": "type",
                "type": "string"
              }
            ],
            "filters": [],
            "format": "table",
            "pagination_mode": "none",
            "parser": "backend",
            "refId": "variable",
            "root_selector": "hits.hits",
            "source": "url",
            "summarizeExpression": "",
            "type": "json",
            "url": "/cds-databudget-conf/_search?q=version:$version AND mission:$mission AND archived:* AND data_category:RAW&size=10000",
            "url_options": {
              "data": "",
              "method": "GET"
            }
          },
          "query": "",
          "queryType": "infinity"
        },
        "refresh": 2,
        "regex": "",
        "skipUrlSync": false,
        "sort": 0,
        "type": "query"
      },
      {
        "allValue": "",
        "current": {
          "selected": true,
          "text": [
            "All"
          ],
          "value": [
            "$__all"
          ]
        },
        "datasource": {
          "type": "yesoreyeram-infinity-datasource",
          "uid": "PD0067CAD9A63E081"
        },
        "definition": "Infinity- (infinity) json",
        "description": "",
        "hide": 2,
        "includeAll": true,
        "multi": true,
        "name": "global_type_disseminated",
        "options": [],
        "query": {
          "infinityQuery": {
            "columns": [
              {
                "selector": "_source.database_type",
                "text": "type",
                "type": "string"
              }
            ],
            "filters": [],
            "format": "table",
            "pagination_mode": "none",
            "parser": "backend",
            "refId": "variable",
            "root_selector": "hits.hits",
            "source": "url",
            "summarizeExpression": "",
            "type": "json",
            "url": "/cds-databudget-conf/_search?q=version:$version AND mission:$mission AND disseminated:* AND data_category:RAW&size=10000",
            "url_options": {
              "data": "",
              "method": "GET"
            }
          },
          "query": "",
          "queryType": "infinity"
        },
        "refresh": 2,
        "regex": "",
        "skipUrlSync": false,
        "sort": 0,
        "type": "query"
      }
    ]
  },
  "time": {
    "from": "now-90d",
    "to": "now"
  },
  "timepicker": {},
  "timezone": "browser",
  "title": "System Technical Budget Thresholds",
  "uid": "aditsrffkv94wd",
  "weekStart": ""
}
